taxonlib/__init__.py
taxonlib/canonical_name.py
taxonlib/types.py
taxonlib/tools/__init__.py
taxonlib/tools/io.py
taxonlib/tools/sources.py
taxonlib/tools/taxa.py
taxonlib-0.0.7.dist-info/licenses/LICENCE.txt
taxonlib-0.0.7.dist-info/METADATA
taxonlib-0.0.7.dist-info/WHEEL
taxonlib-0.0.7.dist-info/top_level.txt
taxonlib-0.0.7.dist-info/RECORD
