Metadata-Version: 2.4
Name: taxonlib
Version: 0.0.7
Summary: A library of tools that help analyse and combine taxa files intended for Naturalis AI MSM deployments
Author-email: Laurens Hogeweg <laurens.hogeweg@naturalis.nl>, Django Brunink <django.brunink@naturalis.nl>
License-Expression: Apache-2.0
Project-URL: Homepage, https://gitlab.com/naturalis/bii/ai/taxonlib
Project-URL: Issues, https://gitlab.com/naturalis/bii/ai/taxonlib/issues
Classifier: Programming Language :: Python :: 3
Classifier: Operating System :: OS Independent
Requires-Python: >=3.10
License-File: LICENCE.txt
Dynamic: license-file
